.travis.yml
licence
readme.md
requirements.txt
setup.cfg
setup.py
tox.ini
doc/readme.md
doc/wireshark.md
doc/device/cf350bt/btsnoop_hci.log.pcap
doc/device/cf350bt/btsnoop_hci.log.rfcomm.txt
doc/device/cf350bt/btsnoop_hci.log.spp.txt
doc/device/cf350bt/readme.md
doc/device/cms50f/AN571-CP210X.pdf
doc/device/cms50f/cms50f-10c4-ea60.txt
doc/device/cms50f/cms50f-v7.0.pdf
doc/device/cms50f/udev-event.txt
doc/device/cms50f/wireshark-setup.pcapng.gz
doc/device/contour-next/contour-next-usb-1a79-7410.txt
doc/device/contour-next/contour-next-usb-2014.pdf
doc/device/contour-next/udev_event.txt
doc/device/ih02/ih02-10c4-ea80.txt
doc/device/ih02/reverse-time.txt
doc/device/ih02/wireshark-connect.pcapng.gz
doc/device/ih02/wireshark-download-single.pcapng.gz
doc/device/ih02/wireshark-download-total.pcapng.gz
doc/device/ih02/wireshark-setting-connect.pcapng.gz
doc/device/ih02/wireshark-setting-datetime.pcapng.gz
doc/device/kd2160/KD2160-180innovations.pdf
doc/device/ketonix/MeasureLoop.java
doc/device/ketonix/ketonix-04d8-f453.txt
doc/device/ketonix/wireshark-calibrate.pcapng.gz
doc/device/ketonix/wireshark-idle.pcapng.gz
doc/device/sony-rcs380/RC-S380_E.pdf
healer.egg-info/PKG-INFO
healer.egg-info/SOURCES.txt
healer.egg-info/dependency_links.txt
healer.egg-info/entry_points.txt
healer.egg-info/not-zip-safe
healer.egg-info/pbr.json
healer.egg-info/requires.txt
healer.egg-info/top_level.txt
src/readme.md
src/main/readme.md
src/main/healer/__init__.py
src/main/healer/config.ini
src/main/healer/config.py
src/main/healer/app/__init__.py
src/main/healer/app/hatcher/__init__.py
src/main/healer/app/hatcher/main.py
src/main/healer/app/service/__init__.py
src/main/healer/app/service/actor.py
src/main/healer/app/service/main.py
src/main/healer/cluster/__init__.py
src/main/healer/cluster/arkon.py
src/main/healer/cluster/bus.py
src/main/healer/cluster/codec.py
src/main/healer/cluster/config.py
src/main/healer/cluster/talk.py
src/main/healer/cluster/wire.py
src/main/healer/cluster/zeromq.py
src/main/healer/cluster/data/__init__.py
src/main/healer/cluster/data/actor.py
src/main/healer/cluster/files/__init__.py
src/main/healer/cluster/files/actor.py
src/main/healer/cluster/hood/__init__.py
