Metadata-Version: 2.1
Name: healer
Version: 0.1.6.dev4
Summary: experimental
Home-page: https://github.com/random-healer/healer
Author: Andrei Pozolotin
Author-email: andrei.pozolotin@gmail.com
License: Apache-2
Keywords: development,repository,operations
Platform: UNKNOWN
Classifier: Development Status :: 4 - Beta
Classifier: Intended Audience :: Developers
Classifier: License :: OSI Approved :: Apache Software License
Classifier: Programming Language :: Python
Classifier: Programming Language :: Python :: 3.7
Classifier: Operating System :: POSIX :: Linux
